{
  "symbol": "META",
  "lastUpdate": "2026-07-06",
  "current": {
    "pe": 21.19,
    "pb": 6.07,
    "ps": 6.88,
    "dividendYield": 0.36,
    "peg": 0.84
  },
  "history5y": {
    "pe": {
      "min": 12.71,
      "max": 31.78,
      "median": 21.19,
      "currentPercentile": 50.0
    },
    "pb": {
      "min": 3.64,
      "max": 8.5,
      "median": 6.07,
      "currentPercentile": 50.0
    }
  },
  "history10y": {
    "pe": {
      "min": 12.71,
      "max": 31.78,
      "median": 21.19,
      "currentPercentile": 50.0
    },
    "pb": {
      "min": 3.64,
      "max": 8.5,
      "median": 6.07,
      "currentPercentile": 50.0
    }
  },
  "source": "yfinance",
  "name": "Meta",
  "market": "US"
}